Workbook

Sheet Summary
A1: MULTIFAMILY ACQUISITION UNDERWRITING — Briarwood Apartments, Livermore, CA
A3: Property Overview & Acquisition
A4: Property Name | C4: Briarwood Apartments
A5: Address | C5: 3819 East Ave, Livermore, CA 94550
A6: Submarket | C6: Tri-Valley / Alameda County, East Bay, CA
A7: Year Built | C7: 1961
A8: Total Units (link) | C8: =Operations!$B$7 -> 64
A9: Purchase Price | C9: 19750000
A10: Price / Unit | C10: =C9/C8 -> 308593.75
A11: Closing Cost % (legal, title, escrow, DD) | C11: 0.015
A12: Closing Costs $ | C12: =C9*C11 -> 296250
A13: Loan Origination Fee % | C13: 0.01
A14: Loan Origination Fee $ | C14: =Debt!$B$5*C13 -> 133000
A15: Total Acquisition Cost | C15: =C9+C12+C14 -> 20179250
A16: Going-in Cap Rate (Yr 1 NOI / Price) | C16: =Operations!$C$42/C9 -> 0.058485873
A17: Loan Amount (link) | C17: =Debt!$B$5 -> 13300000
A18: LTV | C18: =C17/C9 -> 0.67341772
A19: Equity Required | C19: =C15-C17 -> 6879250
A21: 10-Year Return Summary
A22: Exit Cap Rate | C22: =CashFlow!$B$4 -> 0.0675
A23: Hold Period (years) | C23: =CashFlow!$B$6 -> 10
A24: Unlevered IRR | C24: =CashFlow!$B$27 -> 0.074199362
A25: Levered IRR | C25: =CashFlow!$B$28 -> 0.10032787
A26: Equity Multiple | C26: =CashFlow!$B$29 -> 2.2719096
A27: Average Cash-on-Cash | C27: =CashFlow!$B$30 -> 0.062103213
A28: Year 1 DSCR | C28: =CashFlow!$B$32 -> 1.5564395
A29: Year 1 Debt Yield | C29: =CashFlow!$B$33 -> 0.086849323
A31: Notes: Unit count, address, purchase price, and loan terms (amount/rate/IO/amortization) are the actual reported transaction terms. Rent roll, expenses, and going-in NOI are analyst estimates built from Livermore-area market rent comps (RentCafe, Aug 2026) and typical Class B/1960s-vintage East Bay opex benchmarks, since the seller's actual T-12 and rent roll are not publicly disclosed.

Sheet Operations
A1: OPERATIONS — Unit Mix, Rent Roll & 10-Year Operating Statement
A3: Unit Mix & In-Place / Market Rent Roll
A4: Unit Type | B4: # Units | C4: Avg SF | D4: Rent / Unit / Mo | E4: Rent / SF | F4: Monthly Rent (Total) | G4: Annual GPR (Yr 1)
A5: 2BR / 1BA | B5: 63 | C5: 850 | D5: 2450 | E5: =D5/C5 -> 2.8823529 | F5: =B5*D5 -> 154350 | G5: =F5*12 -> 1852200
A6: 3BR / 1BA | B6: 1 | C6: 1100 | D6: 2950 | E6: =D6/C6 -> 2.6818182 | F6: =B6*D6 -> 2950 | G6: =F6*12 -> 35400
A7: Total / Weighted Avg | B7: =SUM(B5:B6) -> 64 | C7: =SUMPRODUCT(B5:B6,C5:C6)/B7 -> 853.90625 | D7: =SUMPRODUCT(B5:B6,D5:D6)/B7 -> 2457.8125 | E7: =F7/SUMPRODUCT(B5:B6,C5:C6) -> 2.8783166 | F7: =SUM(F5:F6) -> 157300 | G7: =SUM(G5:G6) -> 1887600
A8: Source: Marcus & Millichap / YieldPRO transaction report (Jun 2026) for unit count, unit mix, address & sale price. Rents estimated from RentCafe Livermore market data (Aug 2026) — actual seller T-12 / rent roll not publicly available.
A10: Key Operating Assumptions
A11: Market Rent Growth (annual) | B11: 0.03
A12: Vacancy & Credit Loss (% of GPR) | B12: 0.05
A13: Other Income ($ / unit / month) | B13: 35
A14: General Expense Growth (annual) | B14: 0.03
A15: Property Tax Growth (Prop 13 cap) | B15: 0.02
A16: Management Fee (% of EGI) | B16: 0.04
A17: Capital Reserves ($ / unit / yr, Yr 1) | B17: 400
A19: Year 1 Operating Expense Inputs ($ / unit / year, except tax rate)
A20: Property Tax Rate (% of Purchase Price) | B20: 0.012
A21: Insurance ($ / unit / yr) | B21: 950
A22: Repairs & Maintenance ($ / unit / yr) | B22: 1800
A23: Payroll & On-site Mgmt ($ / unit / yr) | B23: 1500
A24: General & Administrative ($ / unit / yr) | B24: 400
A25: Utilities (owner-paid) ($ / unit / yr) | B25: 900
A27: 10-Year Operating Statement
A28: ($ per year) | C28: Year 1 | D28: Year 2 | E28: Year 3 | F28: Year 4 | G28: Year 5 | H28: Year 6 | I28: Year 7 | J28: Year 8 | K28: Year 9 | L28: Year 10
A29: Gross Potential Rent (GPR) | C29: =$G$7 -> 1887600 | D29: =C29*(1+$B$11) -> 1944228 | E29: =D29*(1+$B$11) -> 2002554.8 | F29: =E29*(1+$B$11) -> 2062631.5 | G29: =F29*(1+$B$11) -> 2124510.4 | H29: =G29*(1+$B$11) -> 2188245.7 | I29: =H29*(1+$B$11) -> 2253893.1 | J29: =I29*(1+$B$11) -> 2321509.9 | K29: =J29*(1+$B$11) -> 2391155.2 | L29: =K29*(1+$B$11) -> 2462889.9
A30: Vacancy & Credit Loss | C30: =-C29*$B$12 -> -94380 | D30: =-D29*$B$12 -> -97211.4 | E30: =-E29*$B$12 -> -100127.74 | F30: =-F29*$B$12 -> -103131.57 | G30: =-G29*$B$12 -> -106225.52 | H30: =-H29*$B$12 -> -109412.29 | I30: =-I29*$B$12 -> -112694.66 | J30: =-J29*$B$12 -> -116075.5 | ... L30: =-L29*$B$12 -> -123144.49
A31: Other Income | C31: =$B$13*$B$7*12 -> 26880 | D31: =C31*(1+$B$11) -> 27686.4 | E31: =D31*(1+$B$11) -> 28516.992 | F31: =E31*(1+$B$11) -> 29372.502 | G31: =F31*(1+$B$11) -> 30253.677 | H31: =G31*(1+$B$11) -> 31161.287 | I31: =H31*(1+$B$11) -> 32096.126 | J31: =I31*(1+$B$11) -> 33059.01 | K31: =J31*(1+$B$11) -> 34050.78 | L31: =K31*(1+$B$11) -> 35072.303
A32: Effective Gross Income (EGI) | C32: =C29+C30+C31 -> 1820100 | D32: =D29+D30+D31 -> 1874703 | E32: =E29+E30+E31 -> 1930944.1 | F32: =F29+F30+F31 -> 1988872.4 | G32: =G29+G30+G31 -> 2048538.6 | H32: =H29+H30+H31 -> 2109994.7 | I32: =I29+I30+I31 -> 2173294.6 | J32: =J29+J30+J31 -> 2238493.4 | ... L32: =L29+L30+L31 -> 2374817.7
A33: Operating Expenses:
A34: Property Taxes | C34: =$B$20*Summary!$C$9 -> 237000 | D34: =C34*(1+$B$15) -> 241740 | E34: =D34*(1+$B$15) -> 246574.8 | F34: =E34*(1+$B$15) -> 251506.3 | G34: =F34*(1+$B$15) -> 256536.42 | H34: =G34*(1+$B$15) -> 261667.15 | I34: =H34*(1+$B$15) -> 266900.49 | J34: =I34*(1+$B$15) -> 272238.5 | K34: =J34*(1+$B$15) -> 277683.27 | L34: =K34*(1+$B$15) -> 283236.94
A35: Insurance | C35: =$B$21*$B$7 -> 60800 | D35: =C35*(1+$B$14) -> 62624 | E35: =D35*(1+$B$14) -> 64502.72 | F35: =E35*(1+$B$14) -> 66437.802 | G35: =F35*(1+$B$14) -> 68430.936 | H35: =G35*(1+$B$14) -> 70483.864 | I35: =H35*(1+$B$14) -> 72598.38 | J35: =I35*(1+$B$14) -> 74776.331 | K35: =J35*(1+$B$14) -> 77019.621 | L35: =K35*(1+$B$14) -> 79330.21
A36: Repairs & Maintenance | C36: =$B$22*$B$7 -> 115200 | D36: =C36*(1+$B$14) -> 118656 | E36: =D36*(1+$B$14) -> 122215.68 | F36: =E36*(1+$B$14) -> 125882.15 | G36: =F36*(1+$B$14) -> 129658.61 | H36: =G36*(1+$B$14) -> 133548.37 | I36: =H36*(1+$B$14) -> 137554.82 | J36: =I36*(1+$B$14) -> 141681.47 | K36: =J36*(1+$B$14) -> 145931.91 | L36: =K36*(1+$B$14) -> 150309.87
A37: Payroll & On-site Mgmt | C37: =$B$23*$B$7 -> 96000 | D37: =C37*(1+$B$14) -> 98880 | E37: =D37*(1+$B$14) -> 101846.4 | F37: =E37*(1+$B$14) -> 104901.79 | G37: =F37*(1+$B$14) -> 108048.85 | H37: =G37*(1+$B$14) -> 111290.31 | I37: =H37*(1+$B$14) -> 114629.02 | J37: =I37*(1+$B$14) -> 118067.89 | K37: =J37*(1+$B$14) -> 121609.93 | L37: =K37*(1+$B$14) -> 125258.23
A38: General & Administrative | C38: =$B$24*$B$7 -> 25600 | D38: =C38*(1+$B$14) -> 26368 | E38: =D38*(1+$B$14) -> 27159.04 | F38: =E38*(1+$B$14) -> 27973.811 | G38: =F38*(1+$B$14) -> 28813.026 | H38: =G38*(1+$B$14) -> 29677.416 | I38: =H38*(1+$B$14) -> 30567.739 | J38: =I38*(1+$B$14) -> 31484.771 | K38: =J38*(1+$B$14) -> 32429.314 | L38: =K38*(1+$B$14) -> 33402.194
A39: Utilities | C39: =$B$25*$B$7 -> 57600 | D39: =C39*(1+$B$14) -> 59328 | E39: =D39*(1+$B$14) -> 61107.84 | F39: =E39*(1+$B$14) -> 62941.075 | G39: =F39*(1+$B$14) -> 64829.307 | H39: =G39*(1+$B$14) -> 66774.187 | I39: =H39*(1+$B$14) -> 68777.412 | J39: =I39*(1+$B$14) -> 70840.735 | K39: =J39*(1+$B$14) -> 72965.957 | L39: =K39*(1+$B$14) -> 75154.935
A40: Management Fee | C40: =$B$16*C32 -> 72804 | D40: =$B$16*D32 -> 74988.12 | E40: =$B$16*E32 -> 77237.764 | F40: =$B$16*F32 -> 79554.897 | G40: =$B$16*G32 -> 81941.543 | H40: =$B$16*H32 -> 84399.79 | I40: =$B$16*I32 -> 86931.783 | J40: =$B$16*J32 -> 89539.737 | ... L40: =$B$16*L32 -> 94992.707
A41: Total Operating Expenses | C41: =SUM(C34:C39)+C40 -> 665004 | D41: =SUM(D34:D39)+D40 -> 682584.12 | E41: =SUM(E34:E39)+E40 -> 700644.24 | F41: =SUM(F34:F39)+F40 -> 719197.82 | G41: =SUM(G34:G39)+G40 -> 738258.69 | H41: =SUM(H34:H39)+H40 -> 757841.09 | I41: =SUM(I34:I39)+I40 -> 777959.65 | J41: =SUM(J34:J39)+J40 -> 798629.44 | ... L41: =SUM(L34:L39)+L40 -> 841685.08
A42: Net Operating Income (NOI) | C42: =C32-C41 -> 1155096 | D42: =D32-D41 -> 1192118.9 | E42: =E32-E41 -> 1230299.8 | F42: =F32-F41 -> 1269674.6 | G42: =G32-G41 -> 1310279.9 | H42: =H32-H41 -> 1352153.7 | I42: =I32-I41 -> 1395334.9 | J42: =J32-J41 -> 1439864 | ... L42: =L32-L41 -> 1533132.6
A43: Capital Reserves | C43: =$B$17*$B$7 -> 25600 | D43: =C43*(1+$B$14) -> 26368 | E43: =D43*(1+$B$14) -> 27159.04 | F43: =E43*(1+$B$14) -> 27973.811 | G43: =F43*(1+$B$14) -> 28813.026 | H43: =G43*(1+$B$14) -> 29677.416 | I43: =H43*(1+$B$14) -> 30567.739 | J43: =I43*(1+$B$14) -> 31484.771 | K43: =J43*(1+$B$14) -> 32429.314 | L43: =K43*(1+$B$14) -> 33402.194
A44: Net Cash Flow (pre-debt service) | C44: =C42-C43 -> 1129496 | D44: =D42-D43 -> 1165750.9 | E44: =E42-E43 -> 1203140.8 | F44: =F42-F43 -> 1241700.8 | G44: =G42-G43 -> 1281466.9 | H44: =H42-H43 -> 1322476.2 | I44: =I42-I43 -> 1364767.2 | J44: =J42-J43 -> 1408379.2 | ... L44: =L42-L43 -> 1499730.4

Sheet Debt
A1: DEBT — Loan Terms & 10-Year Amortization Schedule
A3: Loan Terms
A4: Purchase Price (link) | B4: =Summary!$C$9 -> 19750000
A5: Loan Amount | B5: 13300000
A6: Implied LTV | B6: =B5/B4 -> 0.67341772
A7: Interest Rate (annual, fixed) | B7: 0.0558
A8: Monthly Rate | B8: =B7/12 -> 0.00465
A9: Interest-Only Period (years) | B9: 2
A10: Amortization Period (years, post-IO) | B10: 30
A11: Amortization Period (months) | B11: =B10*12 -> 360
A12: Monthly P&I Payment (post-IO) | B12: =-PMT(B8,B11,B5) -> 76184.855
A13: Hold Period (years) | B13: 10
A15: 10-Year Annual Debt Service Schedule
C16: Year 1 | D16: Year 2 | E16: Year 3 | F16: Year 4 | G16: Year 5 | H16: Year 6 | I16: Year 7 | J16: Year 8 | K16: Year 9 | L16: Year 10
A17: Beginning Balance | C17: =$B$5 -> 13300000 | D17: =C21 -> 13300000 | E17: =D21 -> 13300000 | F17: =E21 -> 13123452 | G17: =F21 -> 12936797 | H17: =G21 -> 12739455 | I17: =H21 -> 12530816 | J17: =I21 -> 12310233 | K17: =J21 -> 12077021 | L17: =K21 -> 11830458
A18: Interest Payment | C18: =IF(1<=$B$9,C17*$B$7,-CUMIPMT($B$8,$B$11,$B$5,(1-$B$9-1)*12+1,(1-$B$9)*12,0)) -> 742140 | D18: =IF(2<=$B$9,D17*$B$7,-CUMIPMT($B$8,$B$11,$B$5,(2-$B$9-1)*12+1,(2-$B$9)*12,0)) -> 742140 | E18: =IF(3<=$B$9,E17*$B$7,-CUMIPMT($B$8,$B$11,$B$5,(3-$B$9-1)*12+1,(3-$B$9)*12,0)) -> 737670.17 | F18: =IF(4<=$B$9,F17*$B$7,-CUMIPMT($B$8,$B$11,$B$5,(4-$B$9-1)*12+1,(4-$B$9)*12,0)) -> 727562.89 | G18: =IF(5<=$B$9,G17*$B$7,-CUMIPMT($B$8,$B$11,$B$5,(5-$B$9-1)*12+1,(5-$B$9)*12,0)) -> 716876.97 | H18: =IF(6<=$B$9,H17*$B$7,-CUMIPMT($B$8,$B$11,$B$5,(6-$B$9-1)*12+1,(6-$B$9)*12,0)) -> 705579.29 | I18: =IF(7<=$B$9,I17*$B$7,-CUMIPMT($B$8,$B$11,$B$5,(7-$B$9-1)*12+1,(7-$B$9)*12,0)) -> 693634.83 | J18: =IF(8<=$B$9,J17*$B$7,-CUMIPMT($B$8,$B$11,$B$5,(8-$B$9-1)*12+1,(8-$B$9)*12,0)) -> 681006.55 | K18: =IF(9<=$B$9,K17*$B$7,-CUMIPMT($B$8,$B$11,$B$5,(9-$B$9-1)*12+1,(9-$B$9)*12,0)) -> 667655.31 | L18: =IF(10<=$B$9,L17*$B$7,-CUMIPMT($B$8,$B$11,$B$5,(10-$B$9-1)*12+1,(10-$B$9)*12,0)) -> 653539.72
A19: Principal Payment | C19: =IF(1<=$B$9,0,-CUMPRINC($B$8,$B$11,$B$5,(1-$B$9-1)*12+1,(1-$B$9)*12,0)) -> 0 | D19: =IF(2<=$B$9,0,-CUMPRINC($B$8,$B$11,$B$5,(2-$B$9-1)*12+1,(2-$B$9)*12,0)) -> 0 | E19: =IF(3<=$B$9,0,-CUMPRINC($B$8,$B$11,$B$5,(3-$B$9-1)*12+1,(3-$B$9)*12,0)) -> 176548.09 | F19: =IF(4<=$B$9,0,-CUMPRINC($B$8,$B$11,$B$5,(4-$B$9-1)*12+1,(4-$B$9)*12,0)) -> 186655.37 | G19: =IF(5<=$B$9,0,-CUMPRINC($B$8,$B$11,$B$5,(5-$B$9-1)*12+1,(5-$B$9)*12,0)) -> 197341.29 | H19: =IF(6<=$B$9,0,-CUMPRINC($B$8,$B$11,$B$5,(6-$B$9-1)*12+1,(6-$B$9)*12,0)) -> 208638.96 | I19: =IF(7<=$B$9,0,-CUMPRINC($B$8,$B$11,$B$5,(7-$B$9-1)*12+1,(7-$B$9)*12,0)) -> 220583.43 | J19: =IF(8<=$B$9,0,-CUMPRINC($B$8,$B$11,$B$5,(8-$B$9-1)*12+1,(8-$B$9)*12,0)) -> 233211.71 | K19: =IF(9<=$B$9,0,-CUMPRINC($B$8,$B$11,$B$5,(9-$B$9-1)*12+1,(9-$B$9)*12,0)) -> 246562.94 | L19: =IF(10<=$B$9,0,-CUMPRINC($B$8,$B$11,$B$5,(10-$B$9-1)*12+1,(10-$B$9)*12,0)) -> 260678.53
A20: Total Debt Service | C20: =C18+C19 -> 742140 | D20: =D18+D19 -> 742140 | E20: =E18+E19 -> 914218.26 | F20: =F18+F19 -> 914218.26 | G20: =G18+G19 -> 914218.26 | H20: =H18+H19 -> 914218.26 | I20: =I18+I19 -> 914218.26 | J20: =J18+J19 -> 914218.26 | ... L20: =L18+L19 -> 914218.26
A21: Ending Balance | C21: =C17-C19 -> 13300000 | D21: =D17-D19 -> 13300000 | E21: =E17-E19 -> 13123452 | F21: =F17-F19 -> 12936797 | G21: =G17-G19 -> 12739455 | H21: =H17-H19 -> 12530816 | I21: =I17-I19 -> 12310233 | J21: =J17-J19 -> 12077021 | ... L21: =L17-L19 -> 11569780
A22: DSCR (NOI / Debt Service) | C22: =Operations!C42/C20 -> 1.5564395 | D22: =Operations!D42/D20 -> 1.6063261 | E22: =Operations!E42/E20 -> 1.3457397 | F22: =Operations!F42/F20 -> 1.388809 | G22: =Operations!G42/G20 -> 1.4332244 | H22: =Operations!H42/H20 -> 1.4790272 | I22: =Operations!I42/I20 -> 1.5262602 | J22: =Operations!J42/J20 -> 1.5749674 | ... L22: =Operations!L42/L20 -> 1.6769875
A23: Debt Yield (NOI / Loan Amount) | C23: =Operations!C42/$B$5 -> 0.086849323 | D23: =Operations!D42/$B$5 -> 0.089632998 | E23: =Operations!E42/$B$5 -> 0.092503748 | F23: =Operations!F42/$B$5 -> 0.095464255 | G23: =Operations!G42/$B$5 -> 0.098517285 | H23: =Operations!H42/$B$5 -> 0.10166569 | I23: =Operations!I42/$B$5 -> 0.1049124 | J23: =Operations!J42/$B$5 -> 0.10826045 | ... L23: =Operations!L42/$B$5 -> 0.11527313

Sheet CashFlow
A1: CASH FLOW & RETURNS — 10-Year Levered / Unlevered Analysis
A3: Exit & Sale Assumptions
A4: Exit Cap Rate | B4: 0.0675
A5: Selling Costs (% of gross sale price) | B5: 0.02
A6: Hold Period (years) | B6: =Debt!$B$13 -> 10
A8: 10-Year Cash Flow — Unlevered & Levered
B9: Year 0 | C9: Year 1 | D9: Year 2 | E9: Year 3 | F9: Year 4 | G9: Year 5 | H9: Year 6 | I9: Year 7 | J9: Year 8 | K9: Year 9 | L9: Year 10
A10: Net Operating Income (NOI) | C10: =Operations!C42 -> 1155096 | D10: =Operations!D42 -> 1192118.9 | E10: =Operations!E42 -> 1230299.8 | F10: =Operations!F42 -> 1269674.6 | G10: =Operations!G42 -> 1310279.9 | H10: =Operations!H42 -> 1352153.7 | I10: =Operations!I42 -> 1395334.9 | J10: =Operations!J42 -> 1439864 | ... L10: =Operations!L42 -> 1533132.6
A11: Less: Capital Reserves | C11: =Operations!C43 -> 25600 | D11: =Operations!D43 -> 26368 | E11: =Operations!E43 -> 27159.04 | F11: =Operations!F43 -> 27973.811 | G11: =Operations!G43 -> 28813.026 | H11: =Operations!H43 -> 29677.416 | I11: =Operations!I43 -> 30567.739 | J11: =Operations!J43 -> 31484.771 | ... L11: =Operations!L43 -> 33402.194
A12: Net Operating Cash Flow (Unlevered) | C12: =C10-C11 -> 1129496 | D12: =D10-D11 -> 1165750.9 | E12: =E10-E11 -> 1203140.8 | F12: =F10-F11 -> 1241700.8 | G12: =G10-G11 -> 1281466.9 | H12: =H10-H11 -> 1322476.2 | I12: =I10-I11 -> 1364767.2 | J12: =J10-J11 -> 1408379.2 | ... L12: =L10-L11 -> 1499730.4
A13: Less: Debt Service | C13: =Debt!C20 -> 742140 | D13: =Debt!D20 -> 742140 | E13: =Debt!E20 -> 914218.26 | F13: =Debt!F20 -> 914218.26 | G13: =Debt!G20 -> 914218.26 | H13: =Debt!H20 -> 914218.26 | I13: =Debt!I20 -> 914218.26 | J13: =Debt!J20 -> 914218.26 | ... L13: =Debt!L20 -> 914218.26
A14: Levered Operating Cash Flow | C14: =C12-C13 -> 387356 | D14: =D12-D13 -> 423610.88 | E14: =E12-E13 -> 288922.55 | F14: =F12-F13 -> 327482.52 | G14: =G12-G13 -> 367248.61 | H14: =H12-H13 -> 408257.98 | I14: =I12-I13 -> 450548.94 | J14: =J12-J13 -> 494160.96 | ... L14: =L12-L13 -> 585512.14
A15: Reversion / Sale (Year 10):
A16: Forward NOI (Year 11E) | L16: =L10*(1+Operations!$B$11) -> 1579126.6
A17: Gross Sale Price | L17: =L16/$B$4 -> 23394468
A18: Less: Selling Costs | L18: =L17*$B$5 -> 467889.35
A19: Net Sale Proceeds (before payoff) | L19: =L17-L18 -> 22926578
A20: Less: Loan Payoff | L20: =Debt!L21 -> 11569780
A21: Net Sale Proceeds to Equity | L21: =L19-L20 -> 11356799
A23: Total Unlevered Cash Flow | B23: =-(Summary!$C$9+Summary!$C$12) -> -20046250 | C23: =C12 -> 1129496 | D23: =D12 -> 1165750.9 | E23: =E12 -> 1203140.8 | F23: =F12 -> 1241700.8 | G23: =G12 -> 1281466.9 | H23: =H12 -> 1322476.2 | I23: =I12 -> 1364767.2 | J23: =J12 -> 1408379.2 | K23: =K12 -> 1453353 | L23: =L12+L19 -> 24426309
A24: Total Levered Cash Flow | B24: =-Summary!$C$19 -> -6879250 | C24: =C14 -> 387356 | D24: =D14 -> 423610.88 | E24: =E14 -> 288922.55 | F24: =F14 -> 327482.52 | G24: =G14 -> 367248.61 | H24: =H14 -> 408257.98 | I24: =I14 -> 450548.94 | J24: =J14 -> 494160.96 | K24: =K14 -> 539134.72 | L24: =L14+L21 -> 11942311
A26: Return Metrics
A27: Unlevered IRR | B27: =IRR(B23:L23) -> 0.074199362
A28: Levered IRR | B28: =IRR(B24:L24) -> 0.10032787
A29: Equity Multiple | B29: =SUM(C24:L24)/-B24 -> 2.2719096
A30: Average Cash-on-Cash (operating) | B30: =AVERAGE(C35:L35) -> 0.062103213
A31: Year 1 Cash-on-Cash | B31: =C35 -> 0.056307882
A32: Year 1 DSCR | B32: =Debt!C22 -> 1.5564395
A33: Year 1 Debt Yield | B33: =Debt!C23 -> 0.086849323
A34: Annual Cash-on-Cash Return (levered, operating only)
C35: =C14/Summary!$C$19 -> 0.056307882 | D35: =D14/Summary!$C$19 -> 0.061578062 | E35: =E14/Summary!$C$19 -> 0.041999135 | F35: =F14/Summary!$C$19 -> 0.047604393 | G35: =G14/Summary!$C$19 -> 0.053384977 | H35: =H14/Summary!$C$19 -> 0.059346292 | I35: =I14/Summary!$C$19 -> 0.065493903 | J35: =J14/Summary!$C$19 -> 0.071833551 | ... L35: =L14/Summary!$C$19 -> 0.085112787

Sheet Sensitivity
A1: SENSITIVITY ANALYSIS — Levered IRR
A3: Table 1 — Exit Cap Rate (columns) x Rent Growth (rows) -> Levered IRR
A4: Rent Growth ↓ / Exit Cap → | C4: 0.0625 | D4: 0.065 | E4: 0.0675 | F4: 0.07 | G4: 0.0725
A5: 0.02 | C5: =P26 -> 0.079164244 | D5: =P27 -> 0.071651611 | E5: =P28 -> 0.064210453 | F5: =P29 -> 0.056818302 | G5: =P30 -> 0.049453093
A6: 0.025 | C6: =P36 -> 0.096956137 | D6: =P37 -> 0.089989594 | E6: =P38 -> 0.08313078 | F6: =P39 -> 0.076361058 | G6: =P40 -> 0.069662801
A7: 0.03 | C7: =P46 -> 0.1132855 | D7: =P47 -> 0.10674121 | E7: =P48 -> 0.10032787 | F7: =P49 -> 0.094028827 | G7: =P50 -> 0.087828678
A8: 0.035 | C8: =P56 -> 0.12844626 | D8: =P57 -> 0.12223716 | E8: =P58 -> 0.11617455 | F8: =P59 -> 0.11024285 | G8: =P60 -> 0.10442785
A9: 0.04 | C9: =P66 -> 0.14265147 | D9: =P67 -> 0.13671398 | E9: =P68 -> 0.13093377 | F9: =P69 -> 0.12529583 | G9: =P70 -> 0.11978661
A11: Table 2 — Purchase Price (columns) x Exit Cap Rate (rows) -> Levered IRR
A12: Exit Cap ↓ / Purchase Price → | C12: 18750000 | D12: 19250000 | E12: 19750000 | F12: 20250000 | G12: 20750000
A13: 0.0625 | C13: =P81 -> 0.12923949 | D13: =P94 -> 0.12119135 | E13: =P107 -> 0.1132855 | F13: =P120 -> 0.1055061 | G13: =P133 -> 0.097838278
A14: 0.065 | C14: =P82 -> 0.12303223 | D14: =P95 -> 0.11481901 | E14: =P108 -> 0.10674121 | F14: =P121 -> 0.09878232 | G14: =P134 -> 0.090926809
A15: 0.0675 | C15: =P83 -> 0.11696933 | D15: =P96 -> 0.10858478 | E15: =P109 -> 0.10032787 | F15: =P122 -> 0.092181368 | G15: =P135 -> 0.084128915
A16: 0.07 | C16: =P84 -> 0.11103514 | D16: =P97 -> 0.10247254 | E16: =P110 -> 0.094028827 | F16: =P123 -> 0.08568589 | G16: =P136 -> 0.077426415
A17: 0.0725 | C17: =P85 -> 0.10521541 | D17: =P98 -> 0.096467525 | E17: =P111 -> 0.087828678 | F17: =P124 -> 0.079279729 | G17: =P137 -> 0.070802212
A20: Calculation Detail — supporting Table 1 (do not edit; each scenario recomputes NOI, debt service and exit proceeds from live model assumptions)
A22: Scenario: Rent Growth = 2.0% | B22: 0.02
A23: EGI | C23: =Operations!$G$7*(1+$B$22)^(1-1)*(1-Operations!$B$12)+Operations!$C$31*(1+$B$22)^(1-1) -> 1820100 | D23: =Operations!$G$7*(1+$B$22)^(2-1)*(1-Operations!$B$12)+Operations!$C$31*(1+$B$22)^(2-1) -> 1856502 | E23: =Operations!$G$7*(1+$B$22)^(3-1)*(1-Operations!$B$12)+Operations!$C$31*(1+$B$22)^(3-1) -> 1893632 | F23: =Operations!$G$7*(1+$B$22)^(4-1)*(1-Operations!$B$12)+Operations!$C$31*(1+$B$22)^(4-1) -> 1931504.7 | G23: =Operations!$G$7*(1+$B$22)^(5-1)*(1-Operations!$B$12)+Operations!$C$31*(1+$B$22)^(5-1) -> 1970134.8 | H23: =Operations!$G$7*(1+$B$22)^(6-1)*(1-Operations!$B$12)+Operations!$C$31*(1+$B$22)^(6-1) -> 2009537.5 | I23: =Operations!$G$7*(1+$B$22)^(7-1)*(1-Operations!$B$12)+Operations!$C$31*(1+$B$22)^(7-1) -> 2049728.2 | J23: =Operations!$G$7*(1+$B$22)^(8-1)*(1-Operations!$B$12)+Operations!$C$31*(1+$B$22)^(8-1) -> 2090722.8 | K23: =Operations!$G$7*(1+$B$22)^(9-1)*(1-Operations!$B$12)+Operations!$C$31*(1+$B$22)^(9-1) -> 2132537.2 | L23: =Operations!$G$7*(1+$B$22)^(10-1)*(1-Operations!$B$12)+Operations!$C$31*(1+$B$22)^(10-1) -> 2175188
A24: NOI | C24: =C23-SUM(Operations!C34:C39)-Operations!$B$16*C23 -> 1155096 | D24: =D23-SUM(Operations!D34:D39)-Operations!$B$16*D23 -> 1174645.9 | E24: =E23-SUM(Operations!E34:E39)-Operations!$B$16*E23 -> 1194480.3 | F24: =F23-SUM(Operations!F34:F39)-Operations!$B$16*F23 -> 1214601.6 | G24: =G23-SUM(Operations!G34:G39)-Operations!$B$16*G23 -> 1235012.2 | H24: =H23-SUM(Operations!H34:H39)-Operations!$B$16*H23 -> 1255714.7 | I24: =I23-SUM(Operations!I34:I39)-Operations!$B$16*I23 -> 1276711.2 | J24: =J23-SUM(Operations!J34:J39)-Operations!$B$16*J23 -> 1298004.2 | ... L24: =L23-SUM(Operations!L34:L39)-Operations!$B$16*L23 -> 1341488.1
A25: Levered CF (pre-sale) | C25: =C24-Operations!C43-Debt!C20 -> 387356 | D25: =D24-Operations!D43-Debt!D20 -> 406137.92 | E25: =E24-Operations!E43-Debt!E20 -> 253102.98 | F25: =F24-Operations!F43-Debt!F20 -> 272409.5 | G25: =G24-Operations!G43-Debt!G20 -> 291980.95 | H25: =H24-Operations!H43-Debt!H20 -> 311818.99 | I25: =I24-Operations!I43-Debt!I20 -> 331925.22 | J25: =J24-Operations!J43-Debt!J20 -> 352301.14 | ... L25: =L24-Operations!L43-Debt!L20 -> 393867.64
A26: CF @ Exit Cap 6.25% | B26: =-Summary!$C$19 -> -6879250 | C26: =C25 -> 387356 | D26: =D25 -> 406137.92 | E26: =E25 -> 253102.98 | F26: =F25 -> 272409.5 | G26: =G25 -> 291980.95 | H26: =H25 -> 311818.99 | I26: =I25 -> 331925.22 | J26: =J25 -> 352301.14 | K26: =K25 -> 372948.17 | L26: =L25+((L24*(1+$B$22)/$Q$26)*(1-CashFlow!$B$5)-Debt!L21) -> 10279312 | P26: =IRR(B26:L26) -> 0.079164244 | Q26: 0.0625
A27: CF @ Exit Cap 6.50% | B27: =-Summary!$C$19 -> -6879250 | C27: =C25 -> 387356 | D27: =D25 -> 406137.92 | E27: =E25 -> 253102.98 | F27: =F25 -> 272409.5 | G27: =G25 -> 291980.95 | H27: =H25 -> 311818.99 | I27: =I25 -> 331925.22 | J27: =J25 -> 352301.14 | K27: =K25 -> 372948.17 | L27: =L25+((L24*(1+$B$22)/$Q$27)*(1-CashFlow!$B$5)-Debt!L21) -> 9454111 | P27: =IRR(B27:L27) -> 0.071651611 | Q27: 0.065
A28: CF @ Exit Cap 6.75% | B28: =-Summary!$C$19 -> -6879250 | C28: =C25 -> 387356 | D28: =D25 -> 406137.92 | E28: =E25 -> 253102.98 | F28: =F25 -> 272409.5 | G28: =G25 -> 291980.95 | H28: =H25 -> 311818.99 | I28: =I25 -> 331925.22 | J28: =J25 -> 352301.14 | K28: =K25 -> 372948.17 | L28: =L25+((L24*(1+$B$22)/$Q$28)*(1-CashFlow!$B$5)-Debt!L21) -> 8690036.1 | P28: =IRR(B28:L28) -> 0.064210453 | Q28: 0.0675
A29: CF @ Exit Cap 7.00% | B29: =-Summary!$C$19 -> -6879250 | C29: =C25 -> 387356 | D29: =D25 -> 406137.92 | E29: =E25 -> 253102.98 | F29: =F25 -> 272409.5 | G29: =G25 -> 291980.95 | H29: =H25 -> 311818.99 | I29: =I25 -> 331925.22 | J29: =J25 -> 352301.14 | K29: =K25 -> 372948.17 | L29: =L25+((L24*(1+$B$22)/$Q$29)*(1-CashFlow!$B$5)-Debt!L21) -> 7980537.9 | P29: =IRR(B29:L29) -> 0.056818302 | Q29: 0.07
A30: CF @ Exit Cap 7.25% | B30: =-Summary!$C$19 -> -6879250 | C30: =C25 -> 387356 | D30: =D25 -> 406137.92 | E30: =E25 -> 253102.98 | F30: =F25 -> 272409.5 | G30: =G25 -> 291980.95 | H30: =H25 -> 311818.99 | I30: =I25 -> 331925.22 | J30: =J25 -> 352301.14 | K30: =K25 -> 372948.17 | L30: =L25+((L24*(1+$B$22)/$Q$30)*(1-CashFlow!$B$5)-Debt!L21) -> 7319970.7 | P30: =IRR(B30:L30) -> 0.049453093 | Q30: 0.0725
A32: Scenario: Rent Growth = 2.5% | B32: 0.025
A33: EGI | C33: =Operations!$G$7*(1+$B$32)^(1-1)*(1-Operations!$B$12)+Operations!$C$31*(1+$B$32)^(1-1) -> 1820100 | D33: =Operations!$G$7*(1+$B$32)^(2-1)*(1-Operations!$B$12)+Operations!$C$31*(1+$B$32)^(2-1) -> 1865602.5 | E33: =Operations!$G$7*(1+$B$32)^(3-1)*(1-Operations!$B$12)+Operations!$C$31*(1+$B$32)^(3-1) -> 1912242.6 | F33: =Operations!$G$7*(1+$B$32)^(4-1)*(1-Operations!$B$12)+Operations!$C$31*(1+$B$32)^(4-1) -> 1960048.6 | G33: =Operations!$G$7*(1+$B$32)^(5-1)*(1-Operations!$B$12)+Operations!$C$31*(1+$B$32)^(5-1) -> 2009049.8 | H33: =Operations!$G$7*(1+$B$32)^(6-1)*(1-Operations!$B$12)+Operations!$C$31*(1+$B$32)^(6-1) -> 2059276.1 | I33: =Operations!$G$7*(1+$B$32)^(7-1)*(1-Operations!$B$12)+Operations!$C$31*(1+$B$32)^(7-1) -> 2110758 | J33: =Operations!$G$7*(1+$B$32)^(8-1)*(1-Operations!$B$12)+Operations!$C$31*(1+$B$32)^(8-1) -> 2163526.9 | K33: =Operations!$G$7*(1+$B$32)^(9-1)*(1-Operations!$B$12)+Operations!$C$31*(1+$B$32)^(9-1) -> 2217615.1 | L33: =Operations!$G$7*(1+$B$32)^(10-1)*(1-Operations!$B$12)+Operations!$C$31*(1+$B$32)^(10-1) -> 2273055.5
A34: NOI | C34: =C33-SUM(Operations!C34:C39)-Operations!$B$16*C33 -> 1155096 | D34: =D33-SUM(Operations!D34:D39)-Operations!$B$16*D33 -> 1183382.4 | E34: =E33-SUM(Operations!E34:E39)-Operations!$B$16*E33 -> 1212346.4 | F34: =F33-SUM(Operations!F34:F39)-Operations!$B$16*F33 -> 1242003.8 | G34: =G33-SUM(Operations!G34:G39)-Operations!$B$16*G33 -> 1272370.7 | H34: =H33-SUM(Operations!H34:H39)-Operations!$B$16*H33 -> 1303463.7 | I34: =I33-SUM(Operations!I34:I39)-Operations!$B$16*I33 -> 1335299.8 | J34: =J33-SUM(Operations!J34:J39)-Operations!$B$16*J33 -> 1367896.2 | ... L34: =L33-SUM(Operations!L34:L39)-Operations!$B$16*L33 -> 1435440.9
A35: Levered CF (pre-sale) | C35: =C34-Operations!C43-Debt!C20 -> 387356 | D35: =D34-Operations!D43-Debt!D20 -> 414874.4 | E35: =E34-Operations!E43-Debt!E20 -> 270969.08 | F35: =F34-Operations!F43-Debt!F20 -> 299811.69 | G35: =G34-Operations!G43-Debt!G20 -> 329339.41 | H35: =H34-Operations!H43-Debt!H20 -> 359568.07 | I35: =I34-Operations!I43-Debt!I20 -> 390513.8 | J35: =J34-Operations!J43-Debt!J20 -> 422193.13 | ... L35: =L34-Operations!L43-Debt!L20 -> 487820.45
A36: CF @ Exit Cap 6.25% | B36: =-Summary!$C$19 -> -6879250 | C36: =C35 -> 387356 | D36: =D35 -> 414874.4 | E36: =E35 -> 270969.08 | F36: =F35 -> 299811.69 | G36: =G35 -> 329339.41 | H36: =H35 -> 359568.07 | I36: =I35 -> 390513.8 | J36: =J35 -> 422193.13 | K36: =K35 -> 454622.93 | L36: =L35+((L34*(1+$B$32)/$Q$36)*(1-CashFlow!$B$5)-Debt!L21) -> 11988447 | P36: =IRR(B36:L36) -> 0.096956137 | Q36: 0.0625
A37: CF @ Exit Cap 6.50% | B37: =-Summary!$C$19 -> -6879250 | C37: =C35 -> 387356 | D37: =D35 -> 414874.4 | E37: =E35 -> 270969.08 | F37: =F35 -> 299811.69 | G37: =G35 -> 329339.41 | H37: =H35 -> 359568.07 | I37: =I35 -> 390513.8 | J37: =J35 -> 422193.13 | K37: =K35 -> 454622.93 | L37: =L35+((L34*(1+$B$32)/$Q$37)*(1-CashFlow!$B$5)-Debt!L21) -> 11101124 | P37: =IRR(B37:L37) -> 0.089989594 | Q37: 0.065
A38: CF @ Exit Cap 6.75% | B38: =-Summary!$C$19 -> -6879250 | C38: =C35 -> 387356 | D38: =D35 -> 414874.4 | E38: =E35 -> 270969.08 | F38: =F35 -> 299811.69 | G38: =G35 -> 329339.41 | H38: =H35 -> 359568.07 | I38: =I35 -> 390513.8 | J38: =J35 -> 422193.13 | K38: =K35 -> 454622.93 | L38: =L35+((L34*(1+$B$32)/$Q$38)*(1-CashFlow!$B$5)-Debt!L21) -> 10279528 | P38: =IRR(B38:L38) -> 0.08313078 | Q38: 0.0675
A39: CF @ Exit Cap 7.00% | B39: =-Summary!$C$19 -> -6879250 | C39: =C35 -> 387356 | D39: =D35 -> 414874.4 | E39: =E35 -> 270969.08 | F39: =F35 -> 299811.69 | G39: =G35 -> 329339.41 | H39: =H35 -> 359568.07 | I39: =I35 -> 390513.8 | J39: =J35 -> 422193.13 | K39: =K35 -> 454622.93 | L39: =L35+((L34*(1+$B$32)/$Q$39)*(1-CashFlow!$B$5)-Debt!L21) -> 9516617.7 | P39: =IRR(B39:L39) -> 0.076361058 | Q39: 0.07
A40: CF @ Exit Cap 7.25% | B40: =-Summary!$C$19 -> -6879250 | C40: =C35 -> 387356 | D40: =D35 -> 414874.4 | E40: =E35 -> 270969.08 | F40: =F35 -> 299811.69 | G40: =G35 -> 329339.41 | H40: =H35 -> 359568.07 | I40: =I35 -> 390513.8 | J40: =J35 -> 422193.13 | K40: =K35 -> 454622.93 | L40: =L35+((L34*(1+$B$32)/$Q$40)*(1-CashFlow!$B$5)-Debt!L21) -> 8806321.9 | P40: =IRR(B40:L40) -> 0.069662801 | Q40: 0.0725
A42: Scenario: Rent Growth = 3.0% | B42: 0.03
A43: EGI | C43: =Operations!$G$7*(1+$B$42)^(1-1)*(1-Operations!$B$12)+Operations!$C$31*(1+$B$42)^(1-1) -> 1820100 | D43: =Operations!$G$7*(1+$B$42)^(2-1)*(1-Operations!$B$12)+Operations!$C$31*(1+$B$42)^(2-1) -> 1874703 | E43: =Operations!$G$7*(1+$B$42)^(3-1)*(1-Operations!$B$12)+Operations!$C$31*(1+$B$42)^(3-1) -> 1930944.1 | F43: =Operations!$G$7*(1+$B$42)^(4-1)*(1-Operations!$B$12)+Operations!$C$31*(1+$B$42)^(4-1) -> 1988872.4 | G43: =Operations!$G$7*(1+$B$42)^(5-1)*(1-Operations!$B$12)+Operations!$C$31*(1+$B$42)^(5-1) -> 2048538.6 | H43: =Operations!$G$7*(1+$B$42)^(6-1)*(1-Operations!$B$12)+Operations!$C$31*(1+$B$42)^(6-1) -> 2109994.7 | I43: =Operations!$G$7*(1+$B$42)^(7-1)*(1-Operations!$B$12)+Operations!$C$31*(1+$B$42)^(7-1) -> 2173294.6 | J43: =Operations!$G$7*(1+$B$42)^(8-1)*(1-Operations!$B$12)+Operations!$C$31*(1+$B$42)^(8-1) -> 2238493.4 | K43: =Operations!$G$7*(1+$B$42)^(9-1)*(1-Operations!$B$12)+Operations!$C$31*(1+$B$42)^(9-1) -> 2305648.2 | L43: =Operations!$G$7*(1+$B$42)^(10-1)*(1-Operations!$B$12)+Operations!$C$31*(1+$B$42)^(10-1) -> 2374817.7
A44: NOI | C44: =C43-SUM(Operations!C34:C39)-Operations!$B$16*C43 -> 1155096 | D44: =D43-SUM(Operations!D34:D39)-Operations!$B$16*D43 -> 1192118.9 | E44: =E43-SUM(Operations!E34:E39)-Operations!$B$16*E43 -> 1230299.8 | F44: =F43-SUM(Operations!F34:F39)-Operations!$B$16*F43 -> 1269674.6 | G44: =G43-SUM(Operations!G34:G39)-Operations!$B$16*G43 -> 1310279.9 | H44: =H43-SUM(Operations!H34:H39)-Operations!$B$16*H43 -> 1352153.7 | I44: =I43-SUM(Operations!I34:I39)-Operations!$B$16*I43 -> 1395334.9 | J44: =J43-SUM(Operations!J34:J39)-Operations!$B$16*J43 -> 1439864 | ... L44: =L43-SUM(Operations!L34:L39)-Operations!$B$16*L43 -> 1533132.6
A45: Levered CF (pre-sale) | C45: =C44-Operations!C43-Debt!C20 -> 387356 | D45: =D44-Operations!D43-Debt!D20 -> 423610.88 | E45: =E44-Operations!E43-Debt!E20 -> 288922.55 | F45: =F44-Operations!F43-Debt!F20 -> 327482.52 | G45: =G44-Operations!G43-Debt!G20 -> 367248.61 | H45: =H44-Operations!H43-Debt!H20 -> 408257.98 | I45: =I44-Operations!I43-Debt!I20 -> 450548.94 | J45: =J44-Operations!J43-Debt!J20 -> 494160.96 | ... L45: =L44-Operations!L43-Debt!L20 -> 585512.14
A46: CF @ Exit Cap 6.25% | B46: =-Summary!$C$19 -> -6879250 | C46: =C45 -> 387356 | D46: =D45 -> 423610.88 | E46: =E45 -> 288922.55 | F46: =F45 -> 327482.52 | G46: =G45 -> 367248.61 | H46: =H45 -> 408257.98 | I46: =I45 -> 450548.94 | J46: =J45 -> 494160.96 | K46: =K45 -> 539134.72 | L46: =L45+((L44*(1+$B$42)/$Q$46)*(1-CashFlow!$B$5)-Debt!L21) -> 13776437 | P46: =IRR(B46:L46) -> 0.1132855 | Q46: 0.0625
A47: CF @ Exit Cap 6.50% | B47: =-Summary!$C$19 -> -6879250 | C47: =C45 -> 387356 | D47: =D45 -> 423610.88 | E47: =E45 -> 288922.55 | F47: =F45 -> 327482.52 | G47: =G45 -> 367248.61 | H47: =H45 -> 408257.98 | I47: =I45 -> 450548.94 | J47: =J45 -> 494160.96 | K47: =K45 -> 539134.72 | L47: =L45+((L44*(1+$B$42)/$Q$47)*(1-CashFlow!$B$5)-Debt!L21) -> 12824102 | P47: =IRR(B47:L47) -> 0.10674121 | Q47: 0.065
A48: CF @ Exit Cap 6.75% | B48: =-Summary!$C$19 -> -6879250 | C48: =C45 -> 387356 | D48: =D45 -> 423610.88 | E48: =E45 -> 288922.55 | F48: =F45 -> 327482.52 | G48: =G45 -> 367248.61 | H48: =H45 -> 408257.98 | I48: =I45 -> 450548.94 | J48: =J45 -> 494160.96 | K48: =K45 -> 539134.72 | L48: =L45+((L44*(1+$B$42)/$Q$48)*(1-CashFlow!$B$5)-Debt!L21) -> 11942311 | P48: =IRR(B48:L48) -> 0.10032787 | Q48: 0.0675
A49: CF @ Exit Cap 7.00% | B49: =-Summary!$C$19 -> -6879250 | C49: =C45 -> 387356 | D49: =D45 -> 423610.88 | E49: =E45 -> 288922.55 | F49: =F45 -> 327482.52 | G49: =G45 -> 367248.61 | H49: =H45 -> 408257.98 | I49: =I45 -> 450548.94 | J49: =J45 -> 494160.96 | K49: =K45 -> 539134.72 | L49: =L45+((L44*(1+$B$42)/$Q$49)*(1-CashFlow!$B$5)-Debt!L21) -> 11123504 | P49: =IRR(B49:L49) -> 0.094028827 | Q49: 0.07
A50: CF @ Exit Cap 7.25% | B50: =-Summary!$C$19 -> -6879250 | C50: =C45 -> 387356 | D50: =D45 -> 423610.88 | E50: =E45 -> 288922.55 | F50: =F45 -> 327482.52 | G50: =G45 -> 367248.61 | H50: =H45 -> 408257.98 | I50: =I45 -> 450548.94 | J50: =J45 -> 494160.96 | K50: =K45 -> 539134.72 | L50: =L45+((L44*(1+$B$42)/$Q$50)*(1-CashFlow!$B$5)-Debt!L21) -> 10361167 | P50: =IRR(B50:L50) -> 0.087828678 | Q50: 0.0725
A52: Scenario: Rent Growth = 3.5% | B52: 0.035
A53: EGI | C53: =Operations!$G$7*(1+$B$52)^(1-1)*(1-Operations!$B$12)+Operations!$C$31*(1+$B$52)^(1-1) -> 1820100 | D53: =Operations!$G$7*(1+$B$52)^(2-1)*(1-Operations!$B$12)+Operations!$C$31*(1+$B$52)^(2-1) -> 1883803.5 | E53: =Operations!$G$7*(1+$B$52)^(3-1)*(1-Operations!$B$12)+Operations!$C$31*(1+$B$52)^(3-1) -> 1949736.6 | F53: =Operations!$G$7*(1+$B$52)^(4-1)*(1-Operations!$B$12)+Operations!$C$31*(1+$B$52)^(4-1) -> 2017977.4 | G53: =Operations!$G$7*(1+$B$52)^(5-1)*(1-Operations!$B$12)+Operations!$C$31*(1+$B$52)^(5-1) -> 2088606.6 | H53: =Operations!$G$7*(1+$B$52)^(6-1)*(1-Operations!$B$12)+Operations!$C$31*(1+$B$52)^(6-1) -> 2161707.8 | I53: =Operations!$G$7*(1+$B$52)^(7-1)*(1-Operations!$B$12)+Operations!$C$31*(1+$B$52)^(7-1) -> 2237367.6 | J53: =Operations!$G$7*(1+$B$52)^(8-1)*(1-Operations!$B$12)+Operations!$C$31*(1+$B$52)^(8-1) -> 2315675.5 | K53: =Operations!$G$7*(1+$B$52)^(9-1)*(1-Operations!$B$12)+Operations!$C$31*(1+$B$52)^(9-1) -> 2396724.1 | L53: =Operations!$G$7*(1+$B$52)^(10-1)*(1-Operations!$B$12)+Operations!$C$31*(1+$B$52)^(10-1) -> 2480609.5
A54: NOI | C54: =C53-SUM(Operations!C34:C39)-Operations!$B$16*C53 -> 1155096 | D54: =D53-SUM(Operations!D34:D39)-Operations!$B$16*D53 -> 1200855.4 | E54: =E53-SUM(Operations!E34:E39)-Operations!$B$16*E53 -> 1248340.7 | F54: =F53-SUM(Operations!F34:F39)-Operations!$B$16*F53 -> 1297615.4 | G54: =G53-SUM(Operations!G34:G39)-Operations!$B$16*G53 -> 1348745.2 | H54: =H53-SUM(Operations!H34:H39)-Operations!$B$16*H53 -> 1401798.2 | I54: =I53-SUM(Operations!I34:I39)-Operations!$B$16*I53 -> 1456845 | J54: =J53-SUM(Operations!J34:J39)-Operations!$B$16*J53 -> 1513958.8 | ... L54: =L53-SUM(Operations!L34:L39)-Operations!$B$16*L53 -> 1634692.7
A55: Levered CF (pre-sale) | C55: =C54-Operations!C43-Debt!C20 -> 387356 | D55: =D54-Operations!D43-Debt!D20 -> 432347.36 | E55: =E54-Operations!E43-Debt!E20 -> 306963.38 | F55: =F54-Operations!F43-Debt!F20 -> 355423.31 | G55: =G54-Operations!G43-Debt!G20 -> 405713.91 | H55: =H54-Operations!H43-Debt!H20 -> 457902.55 | I55: =I54-Operations!I43-Debt!I20 -> 512059.05 | J55: =J54-Operations!J43-Debt!J20 -> 568255.74 | ... L55: =L54-Operations!L43-Debt!L20 -> 687072.27
A56: CF @ Exit Cap 6.25% | B56: =-Summary!$C$19 -> -6879250 | C56: =C55 -> 387356 | D56: =D55 -> 432347.36 | E56: =E55 -> 306963.38 | F56: =F55 -> 355423.31 | G56: =G55 -> 405713.91 | H56: =H55 -> 457902.55 | I56: =I55 -> 512059.05 | J56: =J55 -> 568255.74 | K56: =K55 -> 626567.58 | L56: =L55+((L54*(1+$B$52)/$Q$56)*(1-CashFlow!$B$5)-Debt!L21) -> 15646394 | P56: =IRR(B56:L56) -> 0.12844626 | Q56: 0.0625
A57: CF @ Exit Cap 6.50% | B57: =-Summary!$C$19 -> -6879250 | C57: =C55 -> 387356 | D57: =D55 -> 432347.36 | E57: =E55 -> 306963.38 | F57: =F55 -> 355423.31 | G57: =G55 -> 405713.91 | H57: =H55 -> 457902.55 | I57: =I55 -> 512059.05 | J57: =J55 -> 568255.74 | K57: =K55 -> 626567.58 | L57: =L55+((L54*(1+$B$52)/$Q$57)*(1-CashFlow!$B$5)-Debt!L21) -> 14626044 | P57: =IRR(B57:L57) -> 0.12223716 | Q57: 0.065
A58: CF @ Exit Cap 6.75% | B58: =-Summary!$C$19 -> -6879250 | C58: =C55 -> 387356 | D58: =D55 -> 432347.36 | E58: =E55 -> 306963.38 | F58: =F55 -> 355423.31 | G58: =G55 -> 405713.91 | H58: =H55 -> 457902.55 | I58: =I55 -> 512059.05 | J58: =J55 -> 568255.74 | K58: =K55 -> 626567.58 | L58: =L55+((L54*(1+$B$52)/$Q$58)*(1-CashFlow!$B$5)-Debt!L21) -> 13681275 | P58: =IRR(B58:L58) -> 0.11617455 | Q58: 0.0675
A59: CF @ Exit Cap 7.00% | B59: =-Summary!$C$19 -> -6879250 | C59: =C55 -> 387356 | D59: =D55 -> 432347.36 | E59: =E55 -> 306963.38 | F59: =F55 -> 355423.31 | G59: =G55 -> 405713.91 | H59: =H55 -> 457902.55 | I59: =I55 -> 512059.05 | J59: =J55 -> 568255.74 | K59: =K55 -> 626567.58 | L59: =L55+((L54*(1+$B$52)/$Q$59)*(1-CashFlow!$B$5)-Debt!L21) -> 12803990 | P59: =IRR(B59:L59) -> 0.11024285 | Q59: 0.07
A60: CF @ Exit Cap 7.25% | B60: =-Summary!$C$19 -> -6879250 | C60: =C55 -> 387356 | D60: =D55 -> 432347.36 | E60: =E55 -> 306963.38 | F60: =F55 -> 355423.31 | G60: =G55 -> 405713.91 | H60: =H55 -> 457902.55 | I60: =I55 -> 512059.05 | J60: =J55 -> 568255.74 | K60: =K55 -> 626567.58 | L60: =L55+((L54*(1+$B$52)/$Q$60)*(1-CashFlow!$B$5)-Debt!L21) -> 11987207 | P60: =IRR(B60:L60) -> 0.10442785 | Q60: 0.0725
A62: Scenario: Rent Growth = 4.0% | B62: 0.04
A63: EGI | C63: =Operations!$G$7*(1+$B$62)^(1-1)*(1-Operations!$B$12)+Operations!$C$31*(1+$B$62)^(1-1) -> 1820100 | D63: =Operations!$G$7*(1+$B$62)^(2-1)*(1-Operations!$B$12)+Operations!$C$31*(1+$B$62)^(2-1) -> 1892904 | E63: =Operations!$G$7*(1+$B$62)^(3-1)*(1-Operations!$B$12)+Operations!$C$31*(1+$B$62)^(3-1) -> 1968620.2 | F63: =Operations!$G$7*(1+$B$62)^(4-1)*(1-Operations!$B$12)+Operations!$C$31*(1+$B$62)^(4-1) -> 2047365 | G63: =Operations!$G$7*(1+$B$62)^(5-1)*(1-Operations!$B$12)+Operations!$C$31*(1+$B$62)^(5-1) -> 2129259.6 | H63: =Operations!$G$7*(1+$B$62)^(6-1)*(1-Operations!$B$12)+Operations!$C$31*(1+$B$62)^(6-1) -> 2214429.9 | I63: =Operations!$G$7*(1+$B$62)^(7-1)*(1-Operations!$B$12)+Operations!$C$31*(1+$B$62)^(7-1) -> 2303007.1 | J63: =Operations!$G$7*(1+$B$62)^(8-1)*(1-Operations!$B$12)+Operations!$C$31*(1+$B$62)^(8-1) -> 2395127.4 | K63: =Operations!$G$7*(1+$B$62)^(9-1)*(1-Operations!$B$12)+Operations!$C$31*(1+$B$62)^(9-1) -> 2490932.5 | L63: =Operations!$G$7*(1+$B$62)^(10-1)*(1-Operations!$B$12)+Operations!$C$31*(1+$B$62)^(10-1) -> 2590569.8
A64: NOI | C64: =C63-SUM(Operations!C34:C39)-Operations!$B$16*C63 -> 1155096 | D64: =D63-SUM(Operations!D34:D39)-Operations!$B$16*D63 -> 1209591.8 | E64: =E63-SUM(Operations!E34:E39)-Operations!$B$16*E63 -> 1266468.9 | F64: =F63-SUM(Operations!F34:F39)-Operations!$B$16*F63 -> 1325827.4 | G64: =G63-SUM(Operations!G34:G39)-Operations!$B$16*G63 -> 1387772 | H64: =H63-SUM(Operations!H34:H39)-Operations!$B$16*H63 -> 1452411.4 | I64: =I63-SUM(Operations!I34:I39)-Operations!$B$16*I63 -> 1519859 | J64: =J63-SUM(Operations!J34:J39)-Operations!$B$16*J63 -> 1590232.6 | ... L64: =L63-SUM(Operations!L34:L39)-Operations!$B$16*L63 -> 1740254.7
A65: Levered CF (pre-sale) | C65: =C64-Operations!C43-Debt!C20 -> 387356 | D65: =D64-Operations!D43-Debt!D20 -> 441083.84 | E65: =E64-Operations!E43-Debt!E20 -> 325091.58 | F65: =F64-Operations!F43-Debt!F20 -> 383635.37 | G65: =G64-Operations!G43-Debt!G20 -> 444740.75 | H65: =H64-Operations!H43-Debt!H20 -> 508515.77 | I65: =I64-Operations!I43-Debt!I20 -> 575072.99 | J65: =J64-Operations!J43-Debt!J20 -> 644529.6 | ... L65: =L64-Operations!L43-Debt!L20 -> 792634.21
A66: CF @ Exit Cap 6.25% | B66: =-Summary!$C$19 -> -6879250 | C66: =C65 -> 387356 | D66: =D65 -> 441083.84 | E66: =E65 -> 325091.58 | F66: =F65 -> 383635.37 | G66: =G65 -> 444740.75 | H66: =H65 -> 508515.77 | I66: =I65 -> 575072.99 | J66: =J65 -> 644529.6 | K66: =K65 -> 717007.65 | L66: =L65+((L64*(1+$B$62)/$Q$66)*(1-CashFlow!$B$5)-Debt!L21) -> 17601535 | P66: =IRR(B66:L66) -> 0.14265147 | Q66: 0.0625
A67: CF @ Exit Cap 6.50% | B67: =-Summary!$C$19 -> -6879250 | C67: =C65 -> 387356 | D67: =D65 -> 441083.84 | E67: =E65 -> 325091.58 | F67: =F65 -> 383635.37 | G67: =G65 -> 444740.75 | H67: =H65 -> 508515.77 | I67: =I65 -> 575072.99 | J67: =J65 -> 644529.6 | K67: =K65 -> 717007.65 | L67: =L65+((L64*(1+$B$62)/$Q$67)*(1-CashFlow!$B$5)-Debt!L21) -> 16510048 | P67: =IRR(B67:L67) -> 0.13671398 | Q67: 0.065
A68: CF @ Exit Cap 6.75% | B68: =-Summary!$C$19 -> -6879250 | C68: =C65 -> 387356 | D68: =D65 -> 441083.84 | E68: =E65 -> 325091.58 | F68: =F65 -> 383635.37 | G68: =G65 -> 444740.75 | H68: =H65 -> 508515.77 | I68: =I65 -> 575072.99 | J68: =J65 -> 644529.6 | K68: =K65 -> 717007.65 | L68: =L65+((L64*(1+$B$62)/$Q$68)*(1-CashFlow!$B$5)-Debt!L21) -> 15499411 | P68: =IRR(B68:L68) -> 0.13093377 | Q68: 0.0675
A69: CF @ Exit Cap 7.00% | B69: =-Summary!$C$19 -> -6879250 | C69: =C65 -> 387356 | D69: =D65 -> 441083.84 | E69: =E65 -> 325091.58 | F69: =F65 -> 383635.37 | G69: =G65 -> 444740.75 | H69: =H65 -> 508515.77 | I69: =I65 -> 575072.99 | J69: =J65 -> 644529.6 | K69: =K65 -> 717007.65 | L69: =L65+((L64*(1+$B$62)/$Q$69)*(1-CashFlow!$B$5)-Debt!L21) -> 14560962 | P69: =IRR(B69:L69) -> 0.12529583 | Q69: 0.07
A70: CF @ Exit Cap 7.25% | B70: =-Summary!$C$19 -> -6879250 | C70: =C65 -> 387356 | D70: =D65 -> 441083.84 | E70: =E65 -> 325091.58 | F70: =F65 -> 383635.37 | G70: =G65 -> 444740.75 | H70: =H65 -> 508515.77 | I70: =I65 -> 575072.99 | J70: =J65 -> 644529.6 | K70: =K65 -> 717007.65 | L70: =L65+((L64*(1+$B$62)/$Q$70)*(1-CashFlow!$B$5)-Debt!L21) -> 13687235 | P70: =IRR(B70:L70) -> 0.11978661 | Q70: 0.0725
A72: Calculation Detail — supporting Table 2 (do not edit; loan sized at fixed LTV, debt service and payoff recomputed per price scenario)
A74: Scenario: Purchase Price = $18,750,000 | B74: 18750000
A75: Loan Amount (at fixed LTV) | B75: =$B$74*Debt!$B$6 -> 12626582
A76: Equity Required | B76: =$B$74+$B$74*Summary!$C$11+$B$75*Summary!$C$13-$B$75 -> 6530933.5
A77: Monthly P&I (post-IO) | B77: =-PMT(Debt!$B$8,Debt!$B$11,$B$75) -> 72327.394
A78: Loan Balance at Exit (Yr 10) | B78: =$B$75+CUMPRINC(Debt!$B$8,Debt!$B$11,$B$75,1,96,0) -> 10983968
A79: Debt Service | C79: =IF(1<=Debt!$B$9,$B$75*Debt!$B$7,12*$B$77) -> 704563.29 | D79: =IF(2<=Debt!$B$9,$B$75*Debt!$B$7,12*$B$77) -> 704563.29 | E79: =IF(3<=Debt!$B$9,$B$75*Debt!$B$7,12*$B$77) -> 867928.73 | F79: =IF(4<=Debt!$B$9,$B$75*Debt!$B$7,12*$B$77) -> 867928.73 | G79: =IF(5<=Debt!$B$9,$B$75*Debt!$B$7,12*$B$77) -> 867928.73 | H79: =IF(6<=Debt!$B$9,$B$75*Debt!$B$7,12*$B$77) -> 867928.73 | I79: =IF(7<=Debt!$B$9,$B$75*Debt!$B$7,12*$B$77) -> 867928.73 | J79: =IF(8<=Debt!$B$9,$B$75*Debt!$B$7,12*$B$77) -> 867928.73 | K79: =IF(9<=Debt!$B$9,$B$75*Debt!$B$7,12*$B$77) -> 867928.73 | L79: =IF(10<=Debt!$B$9,$B$75*Debt!$B$7,12*$B$77) -> 867928.73
A80: Levered CF (pre-sale) | C80: =Operations!C42-Operations!C43-C79 -> 424932.71 | D80: =Operations!D42-Operations!D43-D79 -> 461187.59 | E80: =Operations!E42-Operations!E43-E79 -> 335212.08 | F80: =Operations!F42-Operations!F43-F79 -> 373772.05 | G80: =Operations!G42-Operations!G43-G79 -> 413538.14 | H80: =Operations!H42-Operations!H43-H79 -> 454547.51 | I80: =Operations!I42-Operations!I43-I79 -> 496838.47 | J80: =Operations!J42-Operations!J43-J79 -> 540450.49 | ... L80: =Operations!L42-Operations!L43-L79 -> 631801.67
A81: CF @ Exit Cap 6.25% | B81: =-$B$76 -> -6530933.5 | C81: =C80 -> 424932.71 | D81: =D80 -> 461187.59 | E81: =E80 -> 335212.08 | F81: =F80 -> 373772.05 | G81: =G80 -> 413538.14 | H81: =H80 -> 454547.51 | I81: =I80 -> 496838.47 | J81: =J80 -> 540450.49 | K81: =K80 -> 585424.25 | L81: =L80+((Operations!L42*(1+Operations!$B$11)/$Q$81)*(1-CashFlow!$B$5)-$B$78) -> 14408538 | P81: =IRR(B81:L81) -> 0.12923949 | Q81: 0.0625
A82: CF @ Exit Cap 6.50% | B82: =-$B$76 -> -6530933.5 | C82: =C80 -> 424932.71 | D82: =D80 -> 461187.59 | E82: =E80 -> 335212.08 | F82: =F80 -> 373772.05 | G82: =G80 -> 413538.14 | H82: =H80 -> 454547.51 | I82: =I80 -> 496838.47 | J82: =J80 -> 540450.49 | K82: =K80 -> 585424.25 | L82: =L80+((Operations!L42*(1+Operations!$B$11)/$Q$82)*(1-CashFlow!$B$5)-$B$78) -> 13456203 | P82: =IRR(B82:L82) -> 0.12303223 | Q82: 0.065
A83: CF @ Exit Cap 6.75% | B83: =-$B$76 -> -6530933.5 | C83: =C80 -> 424932.71 | D83: =D80 -> 461187.59 | E83: =E80 -> 335212.08 | F83: =F80 -> 373772.05 | G83: =G80 -> 413538.14 | H83: =H80 -> 454547.51 | I83: =I80 -> 496838.47 | J83: =J80 -> 540450.49 | K83: =K80 -> 585424.25 | L83: =L80+((Operations!L42*(1+Operations!$B$11)/$Q$83)*(1-CashFlow!$B$5)-$B$78) -> 12574412 | P83: =IRR(B83:L83) -> 0.11696933 | Q83: 0.0675
A84: CF @ Exit Cap 7.00% | B84: =-$B$76 -> -6530933.5 | C84: =C80 -> 424932.71 | D84: =D80 -> 461187.59 | E84: =E80 -> 335212.08 | F84: =F80 -> 373772.05 | G84: =G80 -> 413538.14 | H84: =H80 -> 454547.51 | I84: =I80 -> 496838.47 | J84: =J80 -> 540450.49 | K84: =K80 -> 585424.25 | L84: =L80+((Operations!L42*(1+Operations!$B$11)/$Q$84)*(1-CashFlow!$B$5)-$B$78) -> 11755606 | P84: =IRR(B84:L84) -> 0.11103514 | Q84: 0.07
A85: CF @ Exit Cap 7.25% | B85: =-$B$76 -> -6530933.5 | C85: =C80 -> 424932.71 | D85: =D80 -> 461187.59 | E85: =E80 -> 335212.08 | F85: =F80 -> 373772.05 | G85: =G80 -> 413538.14 | H85: =H80 -> 454547.51 | I85: =I80 -> 496838.47 | J85: =J80 -> 540450.49 | K85: =K80 -> 585424.25 | L85: =L80+((Operations!L42*(1+Operations!$B$11)/$Q$85)*(1-CashFlow!$B$5)-$B$78) -> 10993269 | P85: =IRR(B85:L85) -> 0.10521541 | Q85: 0.0725
A87: Scenario: Purchase Price = $19,250,000 | B87: 19250000
A88: Loan Amount (at fixed LTV) | B88: =$B$87*Debt!$B$6 -> 12963291
A89: Equity Required | B89: =$B$87+$B$87*Summary!$C$11+$B$88*Summary!$C$13-$B$88 -> 6705091.8
A90: Monthly P&I (post-IO) | B90: =-PMT(Debt!$B$8,Debt!$B$11,$B$88) -> 74256.124
A91: Loan Balance at Exit (Yr 10) | B91: =$B$88+CUMPRINC(Debt!$B$8,Debt!$B$11,$B$88,1,96,0) -> 11276874
A92: Debt Service | C92: =IF(1<=Debt!$B$9,$B$88*Debt!$B$7,12*$B$90) -> 723351.65 | D92: =IF(2<=Debt!$B$9,$B$88*Debt!$B$7,12*$B$90) -> 723351.65 | E92: =IF(3<=Debt!$B$9,$B$88*Debt!$B$7,12*$B$90) -> 891073.49 | F92: =IF(4<=Debt!$B$9,$B$88*Debt!$B$7,12*$B$90) -> 891073.49 | G92: =IF(5<=Debt!$B$9,$B$88*Debt!$B$7,12*$B$90) -> 891073.49 | H92: =IF(6<=Debt!$B$9,$B$88*Debt!$B$7,12*$B$90) -> 891073.49 | I92: =IF(7<=Debt!$B$9,$B$88*Debt!$B$7,12*$B$90) -> 891073.49 | J92: =IF(8<=Debt!$B$9,$B$88*Debt!$B$7,12*$B$90) -> 891073.49 | K92: =IF(9<=Debt!$B$9,$B$88*Debt!$B$7,12*$B$90) -> 891073.49 | L92: =IF(10<=Debt!$B$9,$B$88*Debt!$B$7,12*$B$90) -> 891073.49
A93: Levered CF (pre-sale) | C93: =Operations!C42-Operations!C43-C92 -> 406144.35 | D93: =Operations!D42-Operations!D43-D92 -> 442399.23 | E93: =Operations!E42-Operations!E43-E92 -> 312067.31 | F93: =Operations!F42-Operations!F43-F92 -> 350627.29 | G93: =Operations!G42-Operations!G43-G92 -> 390393.37 | H93: =Operations!H42-Operations!H43-H92 -> 431402.74 | I93: =Operations!I42-Operations!I43-I92 -> 473693.7 | J93: =Operations!J42-Operations!J43-J92 -> 517305.72 | ... L93: =Operations!L42-Operations!L43-L92 -> 608656.91
A94: CF @ Exit Cap 6.25% | B94: =-$B$89 -> -6705091.8 | C94: =C93 -> 406144.35 | D94: =D93 -> 442399.23 | E94: =E93 -> 312067.31 | F94: =F93 -> 350627.29 | G94: =G93 -> 390393.37 | H94: =H93 -> 431402.74 | I94: =I93 -> 473693.7 | J94: =J93 -> 517305.72 | K94: =K93 -> 562279.48 | L94: =L93+((Operations!L42*(1+Operations!$B$11)/$Q$94)*(1-CashFlow!$B$5)-$B$91) -> 14092488 | P94: =IRR(B94:L94) -> 0.12119135 | Q94: 0.0625
A95: CF @ Exit Cap 6.50% | B95: =-$B$89 -> -6705091.8 | C95: =C93 -> 406144.35 | D95: =D93 -> 442399.23 | E95: =E93 -> 312067.31 | F95: =F93 -> 350627.29 | G95: =G93 -> 390393.37 | H95: =H93 -> 431402.74 | I95: =I93 -> 473693.7 | J95: =J93 -> 517305.72 | K95: =K93 -> 562279.48 | L95: =L93+((Operations!L42*(1+Operations!$B$11)/$Q$95)*(1-CashFlow!$B$5)-$B$91) -> 13140153 | P95: =IRR(B95:L95) -> 0.11481901 | Q95: 0.065
A96: CF @ Exit Cap 6.75% | B96: =-$B$89 -> -6705091.8 | C96: =C93 -> 406144.35 | D96: =D93 -> 442399.23 | E96: =E93 -> 312067.31 | F96: =F93 -> 350627.29 | G96: =G93 -> 390393.37 | H96: =H93 -> 431402.74 | I96: =I93 -> 473693.7 | J96: =J93 -> 517305.72 | K96: =K93 -> 562279.48 | L96: =L93+((Operations!L42*(1+Operations!$B$11)/$Q$96)*(1-CashFlow!$B$5)-$B$91) -> 12258361 | P96: =IRR(B96:L96) -> 0.10858478 | Q96: 0.0675
A97: CF @ Exit Cap 7.00% | B97: =-$B$89 -> -6705091.8 | C97: =C93 -> 406144.35 | D97: =D93 -> 442399.23 | E97: =E93 -> 312067.31 | F97: =F93 -> 350627.29 | G97: =G93 -> 390393.37 | H97: =H93 -> 431402.74 | I97: =I93 -> 473693.7 | J97: =J93 -> 517305.72 | K97: =K93 -> 562279.48 | L97: =L93+((Operations!L42*(1+Operations!$B$11)/$Q$97)*(1-CashFlow!$B$5)-$B$91) -> 11439555 | P97: =IRR(B97:L97) -> 0.10247254 | Q97: 0.07
A98: CF @ Exit Cap 7.25% | B98: =-$B$89 -> -6705091.8 | C98: =C93 -> 406144.35 | D98: =D93 -> 442399.23 | E98: =E93 -> 312067.31 | F98: =F93 -> 350627.29 | G98: =G93 -> 390393.37 | H98: =H93 -> 431402.74 | I98: =I93 -> 473693.7 | J98: =J93 -> 517305.72 | K98: =K93 -> 562279.48 | L98: =L93+((Operations!L42*(1+Operations!$B$11)/$Q$98)*(1-CashFlow!$B$5)-$B$91) -> 10677218 | P98: =IRR(B98:L98) -> 0.096467525 | Q98: 0.0725
A100: Scenario: Purchase Price = $19,750,000 | B100: 19750000
A101: Loan Amount (at fixed LTV) | B101: =$B$100*Debt!$B$6 -> 13300000
A102: Equity Required | B102: =$B$100+$B$100*Summary!$C$11+$B$101*Summary!$C$13-$B$101 -> 6879250
A103: Monthly P&I (post-IO) | B103: =-PMT(Debt!$B$8,Debt!$B$11,$B$101) -> 76184.855
A104: Loan Balance at Exit (Yr 10) | B104: =$B$101+CUMPRINC(Debt!$B$8,Debt!$B$11,$B$101,1,96,0) -> 11569780
A105: Debt Service | C105: =IF(1<=Debt!$B$9,$B$101*Debt!$B$7,12*$B$103) -> 742140 | D105: =IF(2<=Debt!$B$9,$B$101*Debt!$B$7,12*$B$103) -> 742140 | E105: =IF(3<=Debt!$B$9,$B$101*Debt!$B$7,12*$B$103) -> 914218.26 | F105: =IF(4<=Debt!$B$9,$B$101*Debt!$B$7,12*$B$103) -> 914218.26 | G105: =IF(5<=Debt!$B$9,$B$101*Debt!$B$7,12*$B$103) -> 914218.26 | H105: =IF(6<=Debt!$B$9,$B$101*Debt!$B$7,12*$B$103) -> 914218.26 | I105: =IF(7<=Debt!$B$9,$B$101*Debt!$B$7,12*$B$103) -> 914218.26 | J105: =IF(8<=Debt!$B$9,$B$101*Debt!$B$7,12*$B$103) -> 914218.26 | K105: =IF(9<=Debt!$B$9,$B$101*Debt!$B$7,12*$B$103) -> 914218.26 | L105: =IF(10<=Debt!$B$9,$B$101*Debt!$B$7,12*$B$103) -> 914218.26
A106: Levered CF (pre-sale) | C106: =Operations!C42-Operations!C43-C105 -> 387356 | D106: =Operations!D42-Operations!D43-D105 -> 423610.88 | E106: =Operations!E42-Operations!E43-E105 -> 288922.55 | F106: =Operations!F42-Operations!F43-F105 -> 327482.52 | G106: =Operations!G42-Operations!G43-G105 -> 367248.61 | H106: =Operations!H42-Operations!H43-H105 -> 408257.98 | I106: =Operations!I42-Operations!I43-I105 -> 450548.94 | J106: =Operations!J42-Operations!J43-J105 -> 494160.96 | ... L106: =Operations!L42-Operations!L43-L105 -> 585512.14
A107: CF @ Exit Cap 6.25% | B107: =-$B$102 -> -6879250 | C107: =C106 -> 387356 | D107: =D106 -> 423610.88 | E107: =E106 -> 288922.55 | F107: =F106 -> 327482.52 | G107: =G106 -> 367248.61 | H107: =H106 -> 408257.98 | I107: =I106 -> 450548.94 | J107: =J106 -> 494160.96 | K107: =K106 -> 539134.72 | L107: =L106+((Operations!L42*(1+Operations!$B$11)/$Q$107)*(1-CashFlow!$B$5)-$B$104) -> 13776437 | P107: =IRR(B107:L107) -> 0.1132855 | Q107: 0.0625
A108: CF @ Exit Cap 6.50% | B108: =-$B$102 -> -6879250 | C108: =C106 -> 387356 | D108: =D106 -> 423610.88 | E108: =E106 -> 288922.55 | F108: =F106 -> 327482.52 | G108: =G106 -> 367248.61 | H108: =H106 -> 408257.98 | I108: =I106 -> 450548.94 | J108: =J106 -> 494160.96 | K108: =K106 -> 539134.72 | L108: =L106+((Operations!L42*(1+Operations!$B$11)/$Q$108)*(1-CashFlow!$B$5)-$B$104) -> 12824102 | P108: =IRR(B108:L108) -> 0.10674121 | Q108: 0.065
A109: CF @ Exit Cap 6.75% | B109: =-$B$102 -> -6879250 | C109: =C106 -> 387356 | D109: =D106 -> 423610.88 | E109: =E106 -> 288922.55 | F109: =F106 -> 327482.52 | G109: =G106 -> 367248.61 | H109: =H106 -> 408257.98 | I109: =I106 -> 450548.94 | J109: =J106 -> 494160.96 | K109: =K106 -> 539134.72 | L109: =L106+((Operations!L42*(1+Operations!$B$11)/$Q$109)*(1-CashFlow!$B$5)-$B$104) -> 11942311 | P109: =IRR(B109:L109) -> 0.10032787 | Q109: 0.0675
A110: CF @ Exit Cap 7.00% | B110: =-$B$102 -> -6879250 | C110: =C106 -> 387356 | D110: =D106 -> 423610.88 | E110: =E106 -> 288922.55 | F110: =F106 -> 327482.52 | G110: =G106 -> 367248.61 | H110: =H106 -> 408257.98 | I110: =I106 -> 450548.94 | J110: =J106 -> 494160.96 | K110: =K106 -> 539134.72 | L110: =L106+((Operations!L42*(1+Operations!$B$11)/$Q$110)*(1-CashFlow!$B$5)-$B$104) -> 11123504 | P110: =IRR(B110:L110) -> 0.094028827 | Q110: 0.07
A111: CF @ Exit Cap 7.25% | B111: =-$B$102 -> -6879250 | C111: =C106 -> 387356 | D111: =D106 -> 423610.88 | E111: =E106 -> 288922.55 | F111: =F106 -> 327482.52 | G111: =G106 -> 367248.61 | H111: =H106 -> 408257.98 | I111: =I106 -> 450548.94 | J111: =J106 -> 494160.96 | K111: =K106 -> 539134.72 | L111: =L106+((Operations!L42*(1+Operations!$B$11)/$Q$111)*(1-CashFlow!$B$5)-$B$104) -> 10361167 | P111: =IRR(B111:L111) -> 0.087828678 | Q111: 0.0725
A113: Scenario: Purchase Price = $20,250,000 | B113: 20250000
A114: Loan Amount (at fixed LTV) | B114: =$B$113*Debt!$B$6 -> 13636709
...
